{"id": 123, "groups": {"CONCEAL": {"level": 0, "members": ["BLOCK", "COVER", "HIDE", "MASK"]}, "PARTS OF A WATCH": {"level": 1, "members": ["CROWN", "DIAL", "HAND", "STRAP"]}, "WONDER WOMAN\u2019S COSTUME": {"level": 2, "members": ["LASSO", "SHIELD", "SWORD", "TIARA"]}, "THINGS THAT CAN RUN": {"level": 3, "members": ["CANDIDATE", "FAUCET", "MASCARA", "NOSE"]}}, "startingGroups": [["NOSE", "CROWN", "SWORD", "MASK"], ["DIAL", "FAUCET", "TIARA", "HAND"], ["BLOCK", "MASCARA", "HIDE", "LASSO"], ["CANDIDATE", "SHIELD", "STRAP", "COVER"]]}