{"id": 53, "groups": {"ANIMAL GROUP NAMES": {"level": 0, "members": ["COLONY", "HERD", "PRIDE", "SWARM"]}, "STONED": {"level": 1, "members": ["BAKED", "BLAZED", "HIGH", "LIT"]}, "AP CLASSES": {"level": 2, "members": ["BIO", "CHEM", "GOV", "STATS"]}, "TAXONOMY RANKS": {"level": 3, "members": ["CLASS", "DOMAIN", "FAMILY", "ORDER"]}}, "startingGroups": [["HIGH", "PRIDE", "CLASS", "GOV"], ["ORDER", "CHEM", "LIT", "FAMILY"], ["SWARM", "DOMAIN", "BIO", "COLONY"], ["BAKED", "STATS", "HERD", "BLAZED"]]}