{"id": 14, "groups": {"BEDS": {"level": 0, "members": ["BUNK", "CANOPY", "MURPHY", "TRUNDLE"]}, "FAMOUS BROTHERS": {"level": 1, "members": ["JONAS", "MARX", "WARNER", "WRIGHT"]}, "HONDAS": {"level": 2, "members": ["ACCORD", "CIVIC", "PASSPORT", "PILOT"]}, "VIDEO GAME CHARACTERS": {"level": 3, "members": ["CRASH", "LINK", "MARIO", "SONIC"]}}, "startingGroups": [["CANOPY", "LINK", "PASSPORT", "MARX"], ["PILOT", "SONIC", "WRIGHT", "ACCORD"], ["MURPHY", "CRASH", "CIVIC", "BUNK"], ["MARIO", "JONAS", "TRUNDLE", "WARNER"]]}