{"id": 83, "groups": {"AU NATUREL": {"level": 0, "members": ["BARE", "NAKED", "NUDE", "UNCLAD"]}, "BAKED GOODS": {"level": 1, "members": ["BUN", "DANISH", "MUFFIN", "TURNOVER"]}, "AMERICAN FOOTBALL ACTIONS": {"level": 2, "members": ["FUMBLE", "PUNT", "SACK", "SNAP"]}, "MANICURE STEPS": {"level": 3, "members": ["BUFF", "CLIP", "FILE", "POLISH"]}}, "startingGroups": [["BUN", "SNAP", "CLIP", "BARE"], ["BUFF", "MUFFIN", "POLISH", "SACK"], ["DANISH", "NUDE", "FUMBLE", "TURNOVER"], ["NAKED", "PUNT", "FILE", "UNCLAD"]]}