{"id": 19, "groups": {"OFF-WHITE SHADES": {"level": 0, "members": ["CREAM", "EGGSHELL", "IVORY", "VANILLA"]}, "ANTI-VAMPIRE": {"level": 1, "members": ["CRUCIFIX", "GARLIC", "MIRROR", "STAKE"]}, "KINDS OF MEAT": {"level": 2, "members": ["BEEF", "PORK", "POULTRY", "VENISON"]}, "SYNONYMS FOR ARGUMENT": {"level": 3, "members": ["ROW", "QUARREL", "SPAT", "TIFF"]}}, "startingGroups": [["CREAM", "GARLIC", "PORK", "ROW"], ["MIRROR", "BEEF", "SPAT", "EGGSHELL"], ["POULTRY", "STAKE", "TIFF", "VANILLA"], ["IVORY", "QUARREL", "VENISON", "CRUCIFIX"]]}