{"id":572,"groups":{"UTOPIA":{"level":0,"members":["PARADISE","SEVENTH HEAVEN","SHANGRI-LA","XANADU"]},"THINGS YOU SHAKE":{"level":1,"members":["HAIRSPRAY","MAGIC 8 BALL","SALAD DRESSING","SNOWGLOBE"]},"PROPER NOUN PORTMANTEAUX":{"level":2,"members":["JAZZERCISE","PARALYMPICS","POKÉMON","WIKIPEDIA"]},"ENDING IN SYNONYMS FOR “FRIEND”":{"level":3,"members":["KETCHUM","PAYPAL","PRIMATE","ROSEBUD"]}},"startingGroups":[["HAIRSPRAY","ROSEBUD","POKÉMON","PRIMATE"],["XANADU","JAZZERCISE","KETCHUM","SNOWGLOBE"],["PARALYMPICS","PAYPAL","PARADISE","WIKIPEDIA"],["SEVENTH HEAVEN","SALAD DRESSING","MAGIC 8 BALL","SHANGRI-LA"]]}
