{"id":437,"groups":{"PEACHY KEEN":{"level":0,"members":["NEAT","NIFTY","SUPER","SWELL"]},"PROVIDE MORE DETAILS":{"level":1,"members":["ELABORATE","EXPAND","EXPLAIN","SPECIFY"]},"ABILITY TO DO SOMETHING WELL":{"level":2,"members":["FACILITY","FLAIR","GIFT","KNACK"]},"GROUP OF BUILDINGS":{"level":3,"members":["BLOCK","COMPLEX","COMPOUND","DEVELOPMENT"]}},"startingGroups":[["SUPER","COMPLEX","EXPAND","FACILITY"],["ELABORATE","SWELL","GIFT","BLOCK"],["COMPOUND","FLAIR","NEAT","EXPLAIN"],["KNACK","DEVELOPMENT","SPECIFY","NIFTY"]]}
