{"id":739,"groups":{"QUALITIES OF OVERCOOKED MEAT":{"level":0,"members":["CHEWY","DRY","STRINGY","TOUGH"]},"PLAY SOME ELECTRIC GUITAR":{"level":1,"members":["JAM","NOODLE","SHRED","SOLO"]},"INGREDIENTS IN BUBBLE TEA":{"level":2,"members":["BOBA","MILK","SUGAR","TEA"]},"PLANETS/DWARF PLANET WITH FIRST LETTER CHANGED":{"level":3,"members":["BLUTO","CARS","DARTH","GENUS"]}},"startingGroups":[["CHEWY","NOODLE","CARS","DARTH"],["JAM","BOBA","TOUGH","SHRED"],["SOLO","DRY","SUGAR","BLUTO"],["TEA","GENUS","STRINGY","MILK"]]}
